face_verification/FaceVerificationLibrary.dll
face_verification/FaceVerificationLibrary.lib
face_verification/__init__.py
face_verification/__init__.pyi
face_verification/cpp.cp311-win_amd64.pyd
face_verification/py.typed
face_verification-0.0.1.dist-info/METADATA
face_verification-0.0.1.dist-info/WHEEL
face_verification-0.0.1.dist-info/top_level.txt
face_verification-0.0.1.dist-info/RECORD
