Metadata-Version: 2.1
Name: face-verification
Version: 0.0.1
Summary: Face Verification Library from RealEyes
Author: Realeyes
Author-email: daniel@realeyesit.com
Requires-Dist: numpy >=1.10.0
